redcopy/__init__.py
redcopy/core.py
redcopy/utils/__init__.py
redcopy/utils/data_io.py
redcopy/utils/get_ddl.py
redcopy-0.1.0.dist-info/LICENSE
redcopy-0.1.0.dist-info/METADATA
redcopy-0.1.0.dist-info/WHEEL
redcopy-0.1.0.dist-info/top_level.txt
redcopy-0.1.0.dist-info/RECORD
