Metadata-Version: 2.1
Name: redcopy
Version: 0.1.0
Summary: A simple Python library for easily making a copy of a Redshift Database.
Author-email: Adam Best <besta2010@gmail.com>
Maintainer-email: Adam Best <besta2010@gmail.com>
License: MIT License
Project-URL: repository, https://github.com/adam133/redcopy
Keywords: redshift
Classifier: Development Status :: 3 - Alpha
Classifier: Environment :: Console
Classifier: Intended Audience :: Developers
Classifier: License :: OSI Approved :: MIT License
Classifier: Operating System :: OS Independent
Classifier: Programming Language :: Python
Classifier: Programming Language :: Python :: 3.7
Classifier: Programming Language :: Python :: 3.8
Classifier: Programming Language :: Python :: 3.9
Classifier: Programming Language :: Python :: 3.10
Classifier: Programming Language :: Python :: 3.11
Classifier: Programming Language :: Python :: 3 :: Only
Classifier: Topic :: Software Development :: Libraries :: Python Modules
Requires-Python: >=3.7
License-File: LICENSE
Requires-Dist: redshift-connector (<3,>=2)
